specvizitor/__init__.py
specvizitor/__main__.py
specvizitor/appdata.py
specvizitor/config/__init__.py
specvizitor/config/appearance/__init__.py
specvizitor/config/appearance/appearance.py
specvizitor/config/appearance/qdarktheme/__init__.py
specvizitor/config/appearance/qdarktheme/_color.py
specvizitor/config/appearance/qdarktheme/_icon/__init__.py
specvizitor/config/appearance/qdarktheme/_icon/icon_engine.py
specvizitor/config/appearance/qdarktheme/_icon/svg.py
specvizitor/config/appearance/qdarktheme/_main.py
specvizitor/config/appearance/qdarktheme/_os_appearance/__init__.py
specvizitor/config/appearance/qdarktheme/_os_appearance/_accent/__init__.py
specvizitor/config/appearance/qdarktheme/_os_appearance/_accent/_mac_detect.py
specvizitor/config/appearance/qdarktheme/_os_appearance/listener.py
specvizitor/config/appearance/qdarktheme/_proxy_style.py
specvizitor/config/appearance/qdarktheme/_resources/__init__.py
specvizitor/config/appearance/qdarktheme/_resources/colors.py
specvizitor/config/appearance/qdarktheme/_resources/palette.py
specvizitor/config/appearance/qdarktheme/_resources/standard_icons.py
specvizitor/config/appearance/qdarktheme/_resources/stylesheets.py
specvizitor/config/appearance/qdarktheme/_resources/svg.py
specvizitor/config/appearance/qdarktheme/_style_loader.py
specvizitor/config/appearance/qdarktheme/_template/__init__.py
specvizitor/config/appearance/qdarktheme/_template/engine.py
specvizitor/config/appearance/qdarktheme/_template/filter.py
specvizitor/config/appearance/qdarktheme/_util.py
specvizitor/config/appearance/qdarktheme/qtpy/QtCore/__init__.py
specvizitor/config/appearance/qdarktheme/qtpy/QtGui/__init__.py
specvizitor/config/appearance/qdarktheme/qtpy/QtSvg/__init__.py
specvizitor/config/appearance/qdarktheme/qtpy/QtWidgets/__init__.py
specvizitor/config/appearance/qdarktheme/qtpy/__init__.py
specvizitor/config/appearance/qdarktheme/qtpy/qt_compat.py
specvizitor/config/appearance/qdarktheme/qtpy/qt_version.py
specvizitor-0.6.0.dist-info/METADATA
specvizitor-0.6.0.dist-info/WHEEL
specvizitor-0.6.0.dist-info/entry_points.txt
specvizitor-0.6.0.dist-info/licenses/LICENSE.txt
specvizitor-0.6.0.dist-info/RECORD
