Metadata-Version: 2.4
Name: specvizitor
Version: 0.6.0
Summary: Python GUI application for a visual inspection of astronomical spectroscopic data
License: BSD-3-Clause
License-File: LICENSE.txt
Author: Ivan Kramarenko
Author-email: im.kramarenko@gmail.com
Requires-Python: >=3.10
Classifier: License :: OSI Approved :: BSD License
Classifier: Programming Language :: Python :: 3
Classifier: Programming Language :: Python :: 3.10
Classifier: Programming Language :: Python :: 3.11
Classifier: Programming Language :: Python :: 3.12
Classifier: Programming Language :: Python :: 3.13
Classifier: Programming Language :: Python :: 3.14
Requires-Dist: astropy (>=6.1.0)
Requires-Dist: dacite (==1.8.1)
Requires-Dist: darkdetect (>=0.8.0)
Requires-Dist: pandas (>=2.2.0)
Requires-Dist: pgcolorbar (==1.1.3)
Requires-Dist: pillow (>=10.2.0)
Requires-Dist: platformdirs (>=4.2.0)
Requires-Dist: pyqt5 (>=5.15.10)
Requires-Dist: pyqtgraph (>=0.13.3)
Requires-Dist: qtpy (==2.4.1)
Requires-Dist: rasterio (>=1.3.9)
Requires-Dist: scipy (>=1.12.0)
Project-URL: Repository, https://github.com/ivkram/specvizitor
